GenerateurFacture/__init__.py
GenerateurFacture/api.py
GenerateurFacture/conf.py
GenerateurFacture/generator.py
GenerateurFacture/pdf.py
GenerateurFacture/pohoda.py
InvoiceGenerator/__init__.py
InvoiceGenerator/api.py
InvoiceGenerator/conf.py
InvoiceGenerator/generator.py
InvoiceGenerator/pdf.py
InvoiceGenerator/pohoda.py
InvoiceGenerator/fonts/DejaVuSans-Bold.ttf
InvoiceGenerator/fonts/DejaVuSans.ttf
InvoiceGenerator/fonts/DejaVuSerif-Bold.ttf
InvoiceGenerator/fonts/DejaVuSerif.ttf
InvoiceGenerator/locale/cs/LC_MESSAGES/messages.mo
InvoiceGenerator/locale/cs/LC_MESSAGES/messages.po
InvoiceGenerator/locale/pt_BR/LC_MESSAGES/messages.mo
InvoiceGenerator/locale/pt_BR/LC_MESSAGES/messages.po
generateur_facture-1.0.2.dist-info/METADATA
generateur_facture-1.0.2.dist-info/WHEEL
generateur_facture-1.0.2.dist-info/top_level.txt
generateur_facture-1.0.2.dist-info/RECORD
