Metadata-Version: 2.1
Name: generateur-facture
Version: 1.0.2
Summary: Library to generate PDF invoice.
Home-page: https://github.com/creckx/InvoiceGenerator
Author: Quentin DAVIN
Author-email: quentin@rezonia.fr
License: BSD
Keywords: invoice invoices generator
Classifier: Development Status :: 3 - Alpha
Classifier: Programming Language :: Python
Classifier: Programming Language :: Python :: 3.5
Classifier: Topic :: Utilities
Classifier: License :: OSI Approved :: BSD License
Requires-Dist: reportlab
Requires-Dist: pillow
Requires-Dist: qrplatba (>=0.3.3)
Requires-Dist: babel
